{
  "log-001": {
    "player": "Pirate18721",
    "action": "Leader is Marshall D. Teach",
    "card": "OP09-081"
  },
  "log-002": {
    "player": "TPH64",
    "action": "Leader is Jewelry Bonney",
    "card": "OP07-019"
  },
  "log-003": {
    "player": "Pirate18721",
    "action": "Will select turn order"
  },
  "log-004": {
    "player": "Pirate18721",
    "action": "Chose to go First"
  },
  "log-005": {
    "player": "Pirate18721",
    "action": "Drew card from deck",
    "card": "OP09-088"
  },
  "log-006": {
    "player": "Pirate18721",
    "action": "Drew card from deck",
    "card": "OP09-096"
  },
  "log-007": {
    "player": "Pirate18721",
    "action": "Drew card from deck",
    "card": "OP09-095"
  },
  "log-008": {
    "player": "Pirate18721",
    "action": "Drew card from deck",
    "card": "OP10-082"
  },
  "log-009": {
    "player": "Pirate18721",
    "action": "Drew card from deck",
    "card": "OP09-093"
  },
  "log-010": {
    "player": "Pirate18721",
    "action": "Hand before Mulligan",
    "cards": [
      "OP09-088",
      "OP09-096",
      "OP09-095",
      "OP10-082",
      "OP09-093"
    ],
    "board": [],
    "trash": [],
    "life": 5
  },
  "log-011": {
    "player": "TPH64",
    "action": "Drew card from deck",
    "card": "OP10-032"
  },
  "log-012": {
    "player": "TPH64",
    "action": "Drew card from deck",
    "card": "OP08-030"
  },
  "log-013": {
    "player": "TPH64",
    "action": "Drew card from deck",
    "card": "EB01-015"
  },
  "log-014": {
    "player": "TPH64",
    "action": "Drew card from deck",
    "card": "OP10-032"
  },
  "log-015": {
    "player": "TPH64",
    "action": "Drew card from deck",
    "card": "ST16-004"
  },
  "log-016": {
    "player": "TPH64",
    "action": "Drew card from deck",
    "card": "ST02-007"
  },
  "log-017": {
    "player": "TPH64",
    "action": "Drew card from deck",
    "card": "OP05-030"
  },
  "log-018": {
    "player": "TPH64",
    "action": "Drew card from deck",
    "card": "EB01-015"
  },
  "log-019": {
    "player": "TPH64",
    "action": "Drew card from deck",
    "card": "OP08-030"
  },
  "log-020": {
    "player": "TPH64",
    "action": "Drew card from deck",
    "card": "OP07-029"
  },
  "log-021": {
    "player": "TPH64",
    "action": "Mulligan"
  },
  "log-022": {
    "player": "Pirate18721",
    "action": "Current Hand",
    "cards": [
      "OP09-088",
      "OP09-096",
      "OP09-095",
      "OP10-082",
      "OP09-093"
    ]
  },
  "log-023": {
    "player": "Pirate18721",
    "action": "Current Board",
    "board": []
  },
  "log-024": {
    "player": "Pirate18721",
    "action": "Current Trash",
    "trash": []
  },
  "log-025": {
    "player": "Pirate18721",
    "action": "Current Life",
    "life": 5
  },
  "log-026": {
    "player": "TPH64",
    "action": "Current Hand",
    "cards": [
      "ST02-007",
      "OP05-030",
      "EB01-015",
      "OP08-030",
      "OP07-029"
    ]
  },
  "log-027": {
    "player": "TPH64",
    "action": "Current Trash",
    "trash": []
  },
  "log-028": {
    "player": "TPH64",
    "action": "Current Board",
    "board": []
  },
  "log-029": {
    "player": "TPH64",
    "action": "Current Life",
    "life": 5
  },
  "log-030": {
    "player": "Pirate18721",
    "action": "Draw 1 Don"
  },
  "log-031": {
    "player": "Pirate18721",
    "action": "Reveal and Draw",
    "card": "OP10-082"
  },
  "log-032": {
    "player": "Pirate18721",
    "action": "This is MY AGE!!!! activated",
    "card": "OP09-096",
    "effect": "Trash 2 Remaining Cards"
  },
  "log-033": {
    "player": "Pirate18721",
    "action": "Marshall D. Teach activated",
    "card": "OP09-081",
    "effect": "Trash Kuzan",
    "effect_card": "OP10-082"
  },
  "log-034": {
    "player": "Pirate18721",
    "action": "Marshall D. Teach activated",
    "card": "OP09-081",
    "effect": "Opponent can't activate On Play abilities next turn!"
  },
  "log-035": {
    "player": "Pirate18721",
    "action": "Current Hand",
    "cards": [
      "OP09-088",
      "OP09-095",
      "OP10-082",
      "OP09-093"
    ]
  },
  "log-036": {
    "player": "Pirate18721",
    "action": "Current Board",
    "board": []
  },
  "log-037": {
    "player": "Pirate18721",
    "action": "Current Trash",
    "trash": [
      "OP09-096",
      "OP05-096",
      "OP09-088",
      "OP10-082"
    ]
  },
  "log-038": {
    "player": "Pirate18721",
    "action": "Current Life",
    "life": 5
  },
  "log-039": {
    "player": "TPH64",
    "action": "Current Hand",
    "cards": [
      "ST02-007",
      "OP05-030",
      "EB01-015",
      "OP08-030",
      "OP07-029"
    ]
  },
  "log-040": {
    "player": "TPH64",
    "action": "Current Trash",
    "trash": []
  },
  "log-041": {
    "player": "TPH64",
    "action": "Current Board",
    "board": []
  },
  "log-042": {
    "player": "TPH64",
    "action": "Current Life",
    "life": 5
  },
  "log-043": {
    "player": "Pirate18721",
    "action": "End Turn"
  },
  "log-044": {
    "player": "TPH64",
    "action": "Draw 1 Card"
  },
  "log-045": {
    "player": "TPH64",
    "action": "Drew card from deck",
    "card": "OP07-021"
  },
  "log-046": {
    "player": "TPH64",
    "action": "Draw 2 Don"
  },
  "log-047": {
    "player": "TPH64",
    "action": "Deploy Jewelry Bonney",
    "card": "ST02-007"
  },
  "log-048": {
    "player": "TPH64",
    "action": "End Turn"
  },
  "log-049": {
    "player": "Pirate18721",
    "action": "Current Hand",
    "cards": [
      "OP09-088",
      "OP09-095",
      "OP10-082",
      "OP09-093"
    ]
  },
  "log-050": {
    "player": "Pirate18721",
    "action": "Current Board",
    "board": []
  },
  "log-051": {
    "player": "Pirate18721",
    "action": "Current Trash",
    "trash": [
      "OP09-096",
      "OP05-096",
      "OP09-088",
      "OP10-082"
    ]
  },
  "log-052": {
    "player": "Pirate18721",
    "action": "Current Life",
    "life": 5
  },
  "log-053": {
    "player": "TPH64",
    "action": "Current Hand",
    "cards": [
      "OP05-030",
      "EB01-015",
      "OP08-030",
      "OP07-029",
      "OP07-021"
    ]
  },
  "log-054": {
    "player": "TPH64",
    "action": "Current Trash",
    "trash": []
  },
  "log-055": {
    "player": "TPH64",
    "action": "Current Board",
    "board": [
      "ST02-007"
    ]
  },
  "log-056": {
    "player": "TPH64",
    "action": "Current Life",
    "life": 5
  },
  "log-057": {
    "player": "Pirate18721",
    "action": "Draw 1 Card"
  },
  "log-058": {
    "player": "Pirate18721",
    "action": "Drew card from deck",
    "card": "OP09-086"
  },
  "log-059": {
    "player": "Pirate18721",
    "action": "Draw 2 Don"
  },
  "log-060": {
    "player": "Pirate18721",
    "action": "Deploy Laffitte",
    "card": "OP09-095"
  },
  "log-061": {
    "player": "Pirate18721",
    "action": "Laffitte activated",
    "card": "OP09-095",
    "effect": "Rest Laffitte"
  },
  "log-062": {
    "player": "Pirate18721",
    "action": "Reveal and Draw",
    "card": "OP10-086"
  },
  "log-063": {
    "player": "Pirate18721",
    "action": "Placing Cards on Bottom of Deck"
  },
  "log-064": {
    "player": "Pirate18721",
    "action": "Attach 1 Don to Marshall D. Teach",
    "card": "OP09-081",
    "don_total": 1
  },
  "log-065": {
    "player": "Pirate18721",
    "action": "Marshall D. Teach attacking Jewelry Bonney",
    "attacker_card": "OP09-081",
    "defender_card": "OP07-019"
  },
  "log-066": {
    "player": "TPH64",
    "action": "Discard Scratchmen Apoo for Counter 2000",
    "card": "EB01-015"
  },
  "log-067": {
    "player": "Game",
    "action": "Attack Fails",
    "attacker": {
      "card": "OP09-081",
      "power": 6000
    },
    "defender": {
      "card": "OP07-019",
      "power": 7000
    }
  },
  "log-068": {
    "player": "Pirate18721",
    "action": "Marshall D. Teach activated",
    "card": "OP09-081",
    "effect": "Trash Kuzan",
    "effect_card": "OP10-082"
  },
  "log-069": {
    "player": "Pirate18721",
    "action": "Marshall D. Teach activated",
    "card": "OP09-081",
    "effect": "Opponent can't activate On Play abilities next turn!"
  },
  "log-070": {
    "player": "Pirate18721",
    "action": "Current Hand",
    "cards": [
      "OP09-088",
      "OP09-093",
      "OP09-086",
      "OP10-086"
    ]
  },
  "log-071": {
    "player": "Pirate18721",
    "action": "Current Board",
    "board": [
      "OP09-095"
    ]
  },
  "log-072": {
    "player": "Pirate18721",
    "action": "Current Trash",
    "trash": [
      "OP09-096",
      "OP05-096",
      "OP09-088",
      "OP10-082",
      "OP10-082"
    ]
  },
  "log-073": {
    "player": "Pirate18721",
    "action": "Current Life",
    "life": 5
  },
  "log-074": {
    "player": "TPH64",
    "action": "Current Hand",
    "cards": [
      "OP05-030",
      "OP08-030",
      "OP07-029",
      "OP07-021"
    ]
  },
  "log-075": {
    "player": "TPH64",
    "action": "Current Trash",
    "trash": [
      "EB01-015"
    ]
  },
  "log-076": {
    "player": "TPH64",
    "action": "Current Board",
    "board": [
      "ST02-007"
    ]
  },
  "log-077": {
    "player": "TPH64",
    "action": "Current Life",
    "life": 5
  },
  "log-078": {
    "player": "Pirate18721",
    "action": "End Turn"
  },
  "log-079": {
    "player": "TPH64",
    "action": "Draw 1 Card"
  },
  "log-080": {
    "player": "TPH64",
    "action": "Drew card from deck",
    "card": "OP01-057"
  },
  "log-081": {
    "player": "TPH64",
    "action": "Draw 2 Don"
  },
  "log-082": {
    "player": "TPH64",
    "action": "Jewelry Bonney activated",
    "card": "ST02-007",
    "effect": "Rest Jewelry Bonney"
  },
  "log-083": {
    "player": "TPH64",
    "action": "Reveal and Draw",
    "card": "OP07-021"
  },
  "log-084": {
    "player": "TPH64",
    "action": "Placing Cards on Bottom of Deck"
  },
  "log-085": {
    "player": "TPH64",
    "action": "Attach 2 Don to Jewelry Bonney",
    "card": "OP07-019",
    "don_total": 2
  },
  "log-086": {
    "player": "TPH64",
    "action": "Jewelry Bonney attacking Laffitte",
    "attacker_card": "OP07-019",
    "defender_card": "OP09-095"
  },
  "log-087": {
    "player": "Game",
    "action": "Laffitte Destroyed",
    "attacker": {
      "card": "OP07-019",
      "power": 7000
    },
    "defender": {
      "card": "OP09-095",
      "power": 1000
    }
  },
  "log-088": {
    "player": "TPH64",
    "action": "End Turn"
  },
  "log-089": {
    "player": "Pirate18721",
    "action": "Current Hand",
    "cards": [
      "OP09-088",
      "OP09-093",
      "OP09-086",
      "OP10-086"
    ]
  },
  "log-090": {
    "player": "Pirate18721",
    "action": "Current Board",
    "board": []
  },
  "log-091": {
    "player": "Pirate18721",
    "action": "Current Trash",
    "trash": [
      "OP09-096",
      "OP05-096",
      "OP09-088",
      "OP10-082",
      "OP10-082",
      "OP09-095"
    ]
  },
  "log-092": {
    "player": "Pirate18721",
    "action": "Current Life",
    "life": 5
  },
  "log-093": {
    "player": "TPH64",
    "action": "Current Hand",
    "cards": [
      "OP05-030",
      "OP08-030",
      "OP07-029",
      "OP07-021",
      "OP01-057",
      "OP07-021"
    ]
  },
  "log-094": {
    "player": "TPH64",
    "action": "Current Trash",
    "trash": [
      "EB01-015"
    ]
  },
  "log-095": {
    "player": "TPH64",
    "action": "Current Board",
    "board": [
      "ST02-007"
    ]
  },
  "log-096": {
    "player": "TPH64",
    "action": "Current Life",
    "life": 5
  },
  "log-097": {
    "player": "Pirate18721",
    "action": "Draw 1 Card"
  },
  "log-098": {
    "player": "Pirate18721",
    "action": "Drew card from deck",
    "card": "OP09-098"
  },
  "log-099": {
    "player": "Pirate18721",
    "action": "Draw 2 Don"
  },
  "log-100": {
    "player": "Pirate18721",
    "action": "Deploy Shiryu",
    "card": "OP10-086"
  },
  "log-101": {
    "player": "Pirate18721",
    "action": "Shiryu activated",
    "card": "OP10-086",
    "effect": "Destroy Jewelry Bonney",
    "effect_card": "ST02-007"
  },
  "log-102": {
    "player": "Pirate18721",
    "action": "Attach 1 Don to Marshall D. Teach",
    "card": "OP09-081",
    "don_total": 1
  },
  "log-103": {
    "player": "Pirate18721",
    "action": "Marshall D. Teach attacking Jewelry Bonney",
    "attacker_card": "OP09-081",
    "defender_card": "OP07-019"
  },
  "log-104": {
    "player": "TPH64",
    "action": "Jewelry Bonney activated",
    "card": "OP07-019",
    "effect": "Rest Shiryu",
    "effect_card": "OP10-086"
  },
  "log-105": {
    "player": "Game",
    "action": "Jewelry Bonney hit for 1 damage",
    "attacker": {
      "card": "OP09-081",
      "power": 6000
    },
    "defender": {
      "card": "OP07-019",
      "power": 5000
    }
  },
  "log-106": {
    "player": "Pirate18721",
    "action": "Current Hand",
    "cards": [
      "OP09-088",
      "OP09-093",
      "OP09-086",
      "OP09-098"
    ]
  },
  "log-107": {
    "player": "Pirate18721",
    "action": "Current Board",
    "board": [
      "OP10-086"
    ]
  },
  "log-108": {
    "player": "Pirate18721",
    "action": "Current Trash",
    "trash": [
      "OP09-096",
      "OP05-096",
      "OP09-088",
      "OP10-082",
      "OP10-082",
      "OP09-095"
    ]
  },
  "log-109": {
    "player": "Pirate18721",
    "action": "Current Life",
    "life": 5
  },
  "log-110": {
    "player": "TPH64",
    "action": "Current Hand",
    "cards": [
      "OP05-030",
      "OP08-030",
      "OP07-029",
      "OP07-021",
      "OP01-057",
      "OP07-021",
      "EB01-015"
    ]
  },
  "log-111": {
    "player": "TPH64",
    "action": "Current Trash",
    "trash": [
      "EB01-015",
      "ST02-007"
    ]
  },
  "log-112": {
    "player": "TPH64",
    "action": "Current Board",
    "board": []
  },
  "log-113": {
    "player": "TPH64",
    "action": "Current Life",
    "life": 4
  },
  "log-114": {
    "player": "Pirate18721",
    "action": "End Turn"
  },
  "log-115": {
    "player": "TPH64",
    "action": "Draw 1 Card"
  },
  "log-116": {
    "player": "TPH64",
    "action": "Drew card from deck",
    "card": "ST02-007"
  },
  "log-117": {
    "player": "TPH64",
    "action": "Draw 2 Don"
  },
  "log-118": {
    "player": "TPH64",
    "action": "Deploy Jewelry Bonney",
    "card": "ST02-007"
  },
  "log-119": {
    "player": "TPH64",
    "action": "Jewelry Bonney activated",
    "card": "ST02-007",
    "effect": "Rest Jewelry Bonney"
  },
  "log-120": {
    "player": "TPH64",
    "action": "Reveal and Draw",
    "card": "OP01-039"
  },
  "log-121": {
    "player": "TPH64",
    "action": "Placing Cards on Bottom of Deck"
  },
  "log-122": {
    "player": "TPH64",
    "action": "Deploy Uroge",
    "card": "OP07-021"
  },
  "log-123": {
    "player": "TPH64",
    "action": "Jewelry Bonney attacking Marshall D. Teach",
    "attacker_card": "OP07-019",
    "defender_card": "OP09-081"
  },
  "log-124": {
    "player": "Game",
    "action": "Marshall D. Teach hit for 1 damage",
    "attacker": {
      "card": "OP07-019",
      "power": 5000
    },
    "defender": {
      "card": "OP09-081",
      "power": 5000
    }
  },
  "log-125": {
    "player": "TPH64",
    "action": "Uroge activated",
    "card": "OP07-021",
    "effect": "Activate 1 Don"
  },
  "log-126": {
    "player": "TPH64",
    "action": "End Turn"
  },
  "log-127": {
    "player": "Pirate18721",
    "action": "Current Hand",
    "cards": [
      "OP09-088",
      "OP09-093",
      "OP09-086",
      "OP09-098",
      "OP09-089"
    ]
  },
  "log-128": {
    "player": "Pirate18721",
    "action": "Current Board",
    "board": [
      "OP10-086"
    ]
  },
  "log-129": {
    "player": "Pirate18721",
    "action": "Current Trash",
    "trash": [
      "OP09-096",
      "OP05-096",
      "OP09-088",
      "OP10-082",
      "OP10-082",
      "OP09-095"
    ]
  },
  "log-130": {
    "player": "Pirate18721",
    "action": "Current Life",
    "life": 4
  },
  "log-131": {
    "player": "TPH64",
    "action": "Current Hand",
    "cards": [
      "OP05-030",
      "OP08-030",
      "OP07-029",
      "OP07-021",
      "OP01-057",
      "EB01-015",
      "OP01-039"
    ]
  },
  "log-132": {
    "player": "TPH64",
    "action": "Current Trash",
    "trash": [
      "EB01-015",
      "ST02-007"
    ]
  },
  "log-133": {
    "player": "TPH64",
    "action": "Current Board",
    "board": [
      "ST02-007",
      "OP07-021"
    ]
  },
  "log-134": {
    "player": "TPH64",
    "action": "Current Life",
    "life": 4
  },
  "log-135": {
    "player": "Pirate18721",
    "action": "Draw 1 Card"
  },
  "log-136": {
    "player": "Pirate18721",
    "action": "Drew card from deck",
    "card": "OP09-088"
  },
  "log-137": {
    "player": "Pirate18721",
    "action": "Draw 2 Don"
  },
  "log-138": {
    "player": "Pirate18721",
    "action": "Deploy Jesus Burgess",
    "card": "OP09-086"
  },
  "log-139": {
    "player": "Pirate18721",
    "action": "Attach 2 Don to Marshall D. Teach",
    "card": "OP09-081",
    "don_total": 2
  },
  "log-140": {
    "player": "Pirate18721",
    "action": "Marshall D. Teach attacking Jewelry Bonney",
    "attacker_card": "OP09-081",
    "defender_card": "OP07-019"
  },
  "log-141": {
    "player": "TPH64",
    "action": "Jewelry Bonney activated",
    "card": "OP07-019",
    "effect": "Rest Shiryu",
    "effect_card": "OP10-086"
  },
  "log-142": {
    "player": "Game",
    "action": "Jewelry Bonney hit for 1 damage",
    "attacker": {
      "card": "OP09-081",
      "power": 7000
    },
    "defender": {
      "card": "OP07-019",
      "power": 5000
    }
  },
  "log-143": {
    "player": "Pirate18721",
    "action": "Marshall D. Teach activated",
    "card": "OP09-081",
    "effect": "Trash Shiryu",
    "effect_card": "OP09-088"
  },
  "log-144": {
    "player": "Pirate18721",
    "action": "Marshall D. Teach activated",
    "card": "OP09-081",
    "effect": "Opponent can't activate On Play abilities next turn!"
  },
  "log-145": {
    "player": "Pirate18721",
    "action": "Current Hand",
    "cards": [
      "OP09-093",
      "OP09-098",
      "OP09-089",
      "OP09-088"
    ]
  },
  "log-146": {
    "player": "Pirate18721",
    "action": "Current Board",
    "board": [
      "OP10-086",
      "OP09-086"
    ]
  },
  "log-147": {
    "player": "Pirate18721",
    "action": "Current Trash",
    "trash": [
      "OP09-096",
      "OP05-096",
      "OP09-088",
      "OP10-082",
      "OP10-082",
      "OP09-095",
      "OP09-088"
    ]
  },
  "log-148": {
    "player": "Pirate18721",
    "action": "Current Life",
    "life": 4
  },
  "log-149": {
    "player": "TPH64",
    "action": "Current Hand",
    "cards": [
      "OP05-030",
      "OP08-030",
      "OP07-029",
      "OP07-021",
      "OP01-057",
      "EB01-015",
      "OP01-039",
      "OP05-030"
    ]
  },
  "log-150": {
    "player": "TPH64",
    "action": "Current Trash",
    "trash": [
      "EB01-015",
      "ST02-007"
    ]
  },
  "log-151": {
    "player": "TPH64",
    "action": "Current Board",
    "board": [
      "ST02-007",
      "OP07-021"
    ]
  },
  "log-152": {
    "player": "TPH64",
    "action": "Current Life",
    "life": 3
  },
  "log-153": {
    "player": "Pirate18721",
    "action": "End Turn"
  },
  "log-154": {
    "player": "TPH64",
    "action": "Draw 1 Card"
  },
  "log-155": {
    "player": "TPH64",
    "action": "Drew card from deck",
    "card": "ST02-008"
  },
  "log-156": {
    "player": "TPH64",
    "action": "Draw 2 Don"
  },
  "log-157": {
    "player": "TPH64",
    "action": "Deploy Pedro",
    "card": "OP08-030"
  },
  "log-158": {
    "player": "TPH64",
    "action": "Deploy Donquixote Rosinante",
    "card": "OP05-030"
  },
  "log-159": {
    "player": "TPH64",
    "action": "Jewelry Bonney activated",
    "card": "ST02-007",
    "effect": "Rest Jewelry Bonney"
  },
  "log-160": {
    "player": "TPH64",
    "action": "Reveal and Draw",
    "card": "EB01-012"
  },
  "log-161": {
    "player": "TPH64",
    "action": "Placing Cards on Bottom of Deck"
  },
  "log-162": {
    "player": "TPH64",
    "action": "Attach 1 Don to Jewelry Bonney",
    "card": "OP07-019",
    "don_total": 1
  },
  "log-163": {
    "player": "TPH64",
    "action": "Jewelry Bonney attacking Marshall D. Teach",
    "attacker_card": "OP07-019",
    "defender_card": "OP09-081"
  },
  "log-164": {
    "player": "Pirate18721",
    "action": "Discard Stronger for Counter 2000",
    "card": "OP09-089"
  },
  "log-165": {
    "player": "Game",
    "action": "Attack Fails",
    "attacker": {
      "card": "OP07-019",
      "power": 6000
    },
    "defender": {
      "card": "OP09-081",
      "power": 7000
    }
  },
  "log-166": {
    "player": "TPH64",
    "action": "Uroge activated",
    "card": "OP07-021",
    "effect": "Activate 1 Don"
  },
  "log-167": {
    "player": "TPH64",
    "action": "End Turn"
  },
  "log-168": {
    "player": "Pirate18721",
    "action": "Current Hand",
    "cards": [
      "OP09-093",
      "OP09-098",
      "OP09-088"
    ]
  },
  "log-169": {
    "player": "Pirate18721",
    "action": "Current Board",
    "board": [
      "OP10-086",
      "OP09-086"
    ]
  },
  "log-170": {
    "player": "Pirate18721",
    "action": "Current Trash",
    "trash": [
      "OP09-096",
      "OP05-096",
      "OP09-088",
      "OP10-082",
      "OP10-082",
      "OP09-095",
      "OP09-088",
      "OP09-089"
    ]
  },
  "log-171": {
    "player": "Pirate18721",
    "action": "Current Life",
    "life": 4
  },
  "log-172": {
    "player": "TPH64",
    "action": "Current Hand",
    "cards": [
      "OP05-030",
      "OP07-029",
      "OP07-021",
      "OP01-057",
      "EB01-015",
      "OP01-039",
      "ST02-008",
      "EB01-012"
    ]
  },
  "log-173": {
    "player": "TPH64",
    "action": "Current Trash",
    "trash": [
      "EB01-015",
      "ST02-007"
    ]
  },
  "log-174": {
    "player": "TPH64",
    "action": "Current Board",
    "board": [
      "ST02-007",
      "OP07-021",
      "OP08-030",
      "OP05-030"
    ]
  },
  "log-175": {
    "player": "TPH64",
    "action": "Current Life",
    "life": 3
  },
  "log-176": {
    "player": "Pirate18721",
    "action": "Draw 1 Card"
  },
  "log-177": {
    "player": "Pirate18721",
    "action": "Drew card from deck",
    "card": "OP09-083"
  },
  "log-178": {
    "player": "Pirate18721",
    "action": "Draw 2 Don"
  },
  "log-179": {
    "player": "Pirate18721",
    "action": "Black Hole activated",
    "card": "OP09-098",
    "effect": "Nullify effects of Pedro",
    "effect_card": "OP08-030"
  },
  "log-180": {
    "player": "Pirate18721",
    "action": "Black Hole activated",
    "card": "OP09-098",
    "effect": "Destroy Pedro",
    "effect_card": "OP08-030"
  },
  "log-181": {
    "player": "Pirate18721",
    "action": "Attach 3 Don to Jesus Burgess",
    "card": "OP09-086",
    "don_total": 3
  },
  "log-182": {
    "player": "Pirate18721",
    "action": "Jesus Burgess attacking Jewelry Bonney",
    "attacker_card": "OP09-086",
    "defender_card": "OP07-019"
  },
  "log-183": {
    "player": "TPH64",
    "action": "Jewelry Bonney activated",
    "card": "OP07-019",
    "effect": "Rest Shiryu",
    "effect_card": "OP10-086"
  },
  "log-184": {
    "player": "TPH64",
    "action": "Donquixote Rosinante Blocks",
    "card": "OP05-030"
  },
  "log-185": {
    "player": "Game",
    "action": "Donquixote Rosinante Destroyed",
    "attacker": {
      "card": "OP09-086",
      "power": 10000
    },
    "defender": {
      "card": "OP05-030",
      "power": 1000
    }
  },
  "log-186": {
    "player": "Pirate18721",
    "action": "Attach 2 Don to Marshall D. Teach",
    "card": "OP09-081",
    "don_total": 2
  },
  "log-187": {
    "player": "Pirate18721",
    "action": "Marshall D. Teach attacking Jewelry Bonney",
    "attacker_card": "OP09-081",
    "defender_card": "OP07-019"
  },
  "log-188": {
    "player": "TPH64",
    "action": "Discard Scratchmen Apoo for Counter 2000",
    "card": "ST02-008"
  },
  "log-189": {
    "player": "TPH64",
    "action": "Discard Killer for Counter 1000",
    "card": "OP01-039"
  },
  "log-190": {
    "player": "Game",
    "action": "Attack Fails",
    "attacker": {
      "card": "OP09-081",
      "power": 7000
    },
    "defender": {
      "card": "OP07-019",
      "power": 8000
    }
  },
  "log-191": {
    "player": "Pirate18721",
    "action": "Current Hand",
    "cards": [
      "OP09-093",
      "OP09-088",
      "OP09-083"
    ]
  },
  "log-192": {
    "player": "Pirate18721",
    "action": "Current Board",
    "board": [
      "OP10-086",
      "OP09-086"
    ]
  },
  "log-193": {
    "player": "Pirate18721",
    "action": "Current Trash",
    "trash": [
      "OP09-096",
      "OP05-096",
      "OP09-088",
      "OP10-082",
      "OP10-082",
      "OP09-095",
      "OP09-088",
      "OP09-089",
      "OP09-098"
    ]
  },
  "log-194": {
    "player": "Pirate18721",
    "action": "Current Life",
    "life": 4
  },
  "log-195": {
    "player": "TPH64",
    "action": "Current Hand",
    "cards": [
      "OP05-030",
      "OP07-029",
      "OP07-021",
      "OP01-057",
      "EB01-015",
      "EB01-012"
    ]
  },
  "log-196": {
    "player": "TPH64",
    "action": "Current Trash",
    "trash": [
      "EB01-015",
      "ST02-007",
      "OP08-030",
      "OP05-030",
      "ST02-008",
      "OP01-039"
    ]
  },
  "log-197": {
    "player": "TPH64",
    "action": "Current Board",
    "board": [
      "ST02-007",
      "OP07-021"
    ]
  },
  "log-198": {
    "player": "TPH64",
    "action": "Current Life",
    "life": 3
  },
  "log-199": {
    "player": "Pirate18721",
    "action": "End Turn"
  },
  "log-200": {
    "player": "TPH64",
    "action": "Draw 1 Card"
  },
  "log-201": {
    "player": "TPH64",
    "action": "Drew card from deck",
    "card": "OP10-032"
  },
  "log-202": {
    "player": "TPH64",
    "action": "Draw 2 Don"
  },
  "log-203": {
    "player": "TPH64",
    "action": "Jewelry Bonney activated",
    "card": "ST02-007",
    "effect": "Rest Jewelry Bonney"
  },
  "log-204": {
    "player": "TPH64",
    "action": "Reveal and Draw",
    "card": "ST02-007"
  },
  "log-205": {
    "player": "TPH64",
    "action": "Placing Cards on Bottom of Deck"
  },
  "log-206": {
    "player": "TPH64",
    "action": "Deploy Jewelry Bonney",
    "card": "ST02-007"
  },
  "log-207": {
    "player": "TPH64",
    "action": "Jewelry Bonney activated",
    "card": "ST02-007",
    "effect": "Rest Jewelry Bonney"
  },
  "log-208": {
    "player": "TPH64",
    "action": "Reveal and Draw",
    "card": "OP01-039"
  },
  "log-209": {
    "player": "TPH64",
    "action": "Placing Cards on Bottom of Deck"
  },
  "log-210": {
    "player": "TPH64",
    "action": "Deploy Cavendish",
    "card": "EB01-012"
  },
  "log-211": {
    "player": "TPH64",
    "action": "Cavendish activated",
    "card": "EB01-012",
    "effect": "Activate 2 Don"
  },
  "log-212": {
    "player": "TPH64",
    "action": "Deploy Killer",
    "card": "OP01-039"
  },
  "log-213": {
    "player": "TPH64",
    "action": "Attach 2 Don to Jewelry Bonney",
    "card": "OP07-019",
    "don_total": 2
  },
  "log-214": {
    "player": "TPH64",
    "action": "Jewelry Bonney attacking Marshall D. Teach",
    "attacker_card": "OP07-019",
    "defender_card": "OP09-081"
  },
  "log-215": {
    "player": "Game",
    "action": "Marshall D. Teach hit for 1 damage",
    "attacker": {
      "card": "OP07-019",
      "power": 7000
    },
    "defender": {
      "card": "OP09-081",
      "power": 5000
    }
  },
  "log-216": {
    "player": "Pirate18721",
    "action": "Black Hole activated",
    "card": "OP09-098",
    "effect": "Nullify effects of Cavendish",
    "effect_card": "EB01-012"
  },
  "log-217": {
    "player": "TPH64",
    "action": "Uroge activated",
    "card": "OP07-021",
    "effect": "Activate 1 Don"
  },
  "log-218": {
    "player": "TPH64",
    "action": "Cavendish no longer nullified",
    "card": "EB01-012"
  },
  "log-219": {
    "player": "TPH64",
    "action": "End Turn"
  },
  "log-220": {
    "player": "Pirate18721",
    "action": "Current Hand",
    "cards": [
      "OP09-093",
      "OP09-088",
      "OP09-083"
    ]
  },
  "log-221": {
    "player": "Pirate18721",
    "action": "Current Board",
    "board": [
      "OP10-086",
      "OP09-086"
    ]
  },
  "log-222": {
    "player": "Pirate18721",
    "action": "Current Trash",
    "trash": [
      "OP09-096",
      "OP05-096",
      "OP09-088",
      "OP10-082",
      "OP10-082",
      "OP09-095",
      "OP09-088",
      "OP09-089",
      "OP09-098",
      "OP09-098"
    ]
  },
  "log-223": {
    "player": "Pirate18721",
    "action": "Current Life",
    "life": 3
  },
  "log-224": {
    "player": "TPH64",
    "action": "Current Hand",
    "cards": [
      "OP05-030",
      "OP07-029",
      "OP07-021",
      "OP01-057",
      "EB01-015",
      "OP10-032"
    ]
  },
  "log-225": {
    "player": "TPH64",
    "action": "Current Trash",
    "trash": [
      "EB01-015",
      "ST02-007",
      "OP08-030",
      "OP05-030",
      "ST02-008",
      "OP01-039"
    ]
  },
  "log-226": {
    "player": "TPH64",
    "action": "Current Board",
    "board": [
      "ST02-007",
      "OP07-021",
      "ST02-007",
      "EB01-012",
      "OP01-039"
    ]
  },
  "log-227": {
    "player": "TPH64",
    "action": "Current Life",
    "life": 3
  },
  "log-228": {
    "player": "Pirate18721",
    "action": "Draw 1 Card"
  },
  "log-229": {
    "player": "Pirate18721",
    "action": "Drew card from deck",
    "card": "EB01-051"
  },
  "log-230": {
    "player": "Pirate18721",
    "action": "Draw 2 Don"
  },
  "log-231": {
    "player": "Pirate18721",
    "action": "Deploy Marshall D. Teach",
    "card": "OP09-093"
  },
  "log-232": {
    "player": "Pirate18721",
    "action": "Marshall D. Teach activated",
    "card": "OP09-093",
    "effect": "Nullify effects of Jewelry Bonney",
    "effect_card": "OP07-019"
  },
  "log-233": {
    "player": "Pirate18721",
    "action": "Marshall D. Teach activated",
    "card": "OP09-093",
    "effect": "Cavendish can't attack next turn",
    "effect_card": "EB01-012"
  },
  "log-234": {
    "player": "Pirate18721",
    "action": "Marshall D. Teach activated",
    "card": "OP09-093",
    "effect": "Nullify effects of Cavendish until next turn end!",
    "effect_card": "EB01-012"
  },
  "log-235": {
    "player": "Pirate18721",
    "action": "Jesus Burgess attacking Jewelry Bonney",
    "attacker_card": "OP09-086",
    "defender_card": "OP07-019"
  },
  "log-236": {
    "player": "Game",
    "action": "Jewelry Bonney hit for 1 damage",
    "attacker": {
      "card": "OP09-086",
      "power": 7000
    },
    "defender": {
      "card": "OP07-019",
      "power": 5000
    }
  },
  "log-237": {
    "player": "Pirate18721",
    "action": "Shiryu attacking Jewelry Bonney",
    "attacker_card": "OP10-086",
    "defender_card": "OP07-019"
  },
  "log-238": {
    "player": "TPH64",
    "action": "Discard Uroge for Counter 1000",
    "card": "OP07-021"
  },
  "log-239": {
    "player": "Game",
    "action": "Attack Fails",
    "attacker": {
      "card": "OP10-086",
      "power": 5000
    },
    "defender": {
      "card": "OP07-019",
      "power": 6000
    }
  },
  "log-240": {
    "player": "Pirate18721",
    "action": "Marshall D. Teach activated",
    "card": "OP09-081",
    "effect": "Trash Van Augur",
    "effect_card": "OP09-083"
  },
  "log-241": {
    "player": "Pirate18721",
    "action": "Marshall D. Teach activated",
    "card": "OP09-081",
    "effect": "Opponent can't activate On Play abilities next turn!"
  },
  "log-242": {
    "player": "Pirate18721",
    "action": "Marshall D. Teach attacking Jewelry Bonney",
    "attacker_card": "OP09-081",
    "defender_card": "OP07-019"
  },
  "log-243": {
    "player": "TPH64",
    "action": "Discard Donquixote Rosinante for Counter 1000",
    "card": "OP05-030"
  },
  "log-244": {
    "player": "Game",
    "action": "Attack Fails",
    "attacker": {
      "card": "OP09-081",
      "power": 5000
    },
    "defender": {
      "card": "OP07-019",
      "power": 6000
    }
  },
  "log-245": {
    "player": "Pirate18721",
    "action": "Jewelry Bonney no longer nullified",
    "card": "OP07-019"
  },
  "log-246": {
    "player": "Pirate18721",
    "action": "Current Hand",
    "cards": [
      "OP09-088",
      "EB01-051"
    ]
  },
  "log-247": {
    "player": "Pirate18721",
    "action": "Current Board",
    "board": [
      "OP10-086",
      "OP09-086",
      "OP09-093"
    ]
  },
  "log-248": {
    "player": "Pirate18721",
    "action": "Current Trash",
    "trash": [
      "OP09-096",
      "OP05-096",
      "OP09-088",
      "OP10-082",
      "OP10-082",
      "OP09-095",
      "OP09-088",
      "OP09-089",
      "OP09-098",
      "OP09-098",
      "OP09-083"
    ]
  },
  "log-249": {
    "player": "Pirate18721",
    "action": "Current Life",
    "life": 3
  },
  "log-250": {
    "player": "TPH64",
    "action": "Current Hand",
    "cards": [
      "OP07-029",
      "OP01-057",
      "EB01-015",
      "OP10-032",
      "OP08-023"
    ]
  },
  "log-251": {
    "player": "TPH64",
    "action": "Current Trash",
    "trash": [
      "EB01-015",
      "ST02-007",
      "OP08-030",
      "OP05-030",
      "ST02-008",
      "OP01-039",
      "OP07-021",
      "OP05-030"
    ]
  },
  "log-252": {
    "player": "TPH64",
    "action": "Current Board",
    "board": [
      "ST02-007",
      "OP07-021",
      "ST02-007",
      "EB01-012",
      "OP01-039"
    ]
  },
  "log-253": {
    "player": "TPH64",
    "action": "Current Life",
    "life": 2
  },
  "log-254": {
    "player": "Pirate18721",
    "action": "End Turn"
  },
  "log-255": {
    "player": "TPH64",
    "action": "Draw 1 Card"
  },
  "log-256": {
    "player": "TPH64",
    "action": "Drew card from deck",
    "card": "OP01-051"
  },
  "log-257": {
    "player": "TPH64",
    "action": "Jewelry Bonney activated",
    "card": "ST02-007",
    "effect": "Rest Jewelry Bonney"
  },
  "log-258": {
    "player": "TPH64",
    "action": "Reveal and Draw",
    "card": "ST02-007"
  },
  "log-259": {
    "player": "TPH64",
    "action": "Placing Cards on Bottom of Deck"
  },
  "log-260": {
    "player": "TPH64",
    "action": "Jewelry Bonney activated",
    "card": "ST02-007",
    "effect": "Rest Jewelry Bonney"
  },
  "log-261": {
    "player": "TPH64",
    "action": "Reveal and Draw",
    "card": "OP01-039"
  },
  "log-262": {
    "player": "TPH64",
    "action": "Placing Cards on Bottom of Deck"
  },
  "log-263": {
    "player": "TPH64",
    "action": "Trash Jewelry Bonney",
    "card": "ST02-007"
  },
  "log-264": {
    "player": "TPH64",
    "action": "Deploy Carrot",
    "card": "OP08-023"
  },
  "log-265": {
    "player": "TPH64",
    "action": "Trash Jewelry Bonney",
    "card": "ST02-007"
  },
  "log-266": {
    "player": "TPH64",
    "action": "Deploy Killer",
    "card": "OP01-039"
  },
  "log-267": {
    "player": "TPH64",
    "action": "Attach 1 Don to Jewelry Bonney",
    "card": "OP07-019",
    "don_total": 1
  },
  "log-268": {
    "player": "TPH64",
    "action": "Jewelry Bonney attacking Marshall D. Teach",
    "attacker_card": "OP07-019",
    "defender_card": "OP09-081"
  },
  "log-269": {
    "player": "Pirate18721",
    "action": "Discard Shiryu for Counter 2000",
    "card": "OP09-088"
  },
  "log-270": {
    "player": "Game",
    "action": "Attack Fails",
    "attacker": {
      "card": "OP07-019",
      "power": 6000
    },
    "defender": {
      "card": "OP09-081",
      "power": 7000
    }
  },
  "log-271": {
    "player": "TPH64",
    "action": "Uroge activated",
    "card": "OP07-021",
    "effect": "Activate 1 Don"
  },
  "log-272": {
    "player": "TPH64",
    "action": "Cavendish is no longer blocked from attacking",
    "card": "EB01-012"
  },
  "log-273": {
    "player": "TPH64",
    "action": "Cavendish no longer nullified",
    "card": "EB01-012"
  },
  "log-274": {
    "player": "TPH64",
    "action": "End Turn"
  },
  "log-275": {
    "player": "Pirate18721",
    "action": "Current Hand",
    "cards": [
      "EB01-051"
    ]
  },
  "log-276": {
    "player": "Pirate18721",
    "action": "Current Board",
    "board": [
      "OP10-086",
      "OP09-086",
      "OP09-093"
    ]
  },
  "log-277": {
    "player": "Pirate18721",
    "action": "Current Trash",
    "trash": [
      "OP09-096",
      "OP05-096",
      "OP09-088",
      "OP10-082",
      "OP10-082",
      "OP09-095",
      "OP09-088",
      "OP09-089",
      "OP09-098",
      "OP09-098",
      "OP09-083",
      "OP09-088"
    ]
  },
  "log-278": {
    "player": "Pirate18721",
    "action": "Current Life",
    "life": 3
  },
  "log-279": {
    "player": "TPH64",
    "action": "Current Hand",
    "cards": [
      "OP07-029",
      "OP01-057",
      "EB01-015",
      "OP10-032",
      "OP01-051",
      "ST02-007"
    ]
  },
  "log-280": {
    "player": "TPH64",
    "action": "Current Trash",
    "trash": [
      "EB01-015",
      "ST02-007",
      "OP08-030",
      "OP05-030",
      "ST02-008",
      "OP01-039",
      "OP07-021",
      "OP05-030",
      "ST02-007",
      "ST02-007"
    ]
  },
  "log-281": {
    "player": "TPH64",
    "action": "Current Board",
    "board": [
      "OP07-021",
      "EB01-012",
      "OP01-039",
      "OP08-023",
      "OP01-039"
    ]
  },
  "log-282": {
    "player": "TPH64",
    "action": "Current Life",
    "life": 2
  },
  "log-283": {
    "player": "Pirate18721",
    "action": "Draw 1 Card"
  },
  "log-284": {
    "player": "Pirate18721",
    "action": "Drew card from deck",
    "card": "OP10-098"
  },
  "log-285": {
    "player": "Pirate18721",
    "action": "Liberation activated",
    "card": "OP10-098",
    "effect": "Destroy Uroge",
    "effect_card": "OP07-021"
  },
  "log-286": {
    "player": "Pirate18721",
    "action": "Liberation activated",
    "card": "OP10-098",
    "effect": "Destroy Cavendish",
    "effect_card": "EB01-012"
  },
  "log-287": {
    "player": "Pirate18721",
    "action": "Shigan (Finger Gun) activated",
    "card": "EB01-051",
    "effect": "Trash 2 Cards from Deck"
  },
  "log-288": {
    "player": "Pirate18721",
    "action": "Shigan (Finger Gun) activated",
    "card": "EB01-051",
    "effect": "Destroy Carrot",
    "effect_card": "OP08-023"
  },
  "log-289": {
    "player": "Pirate18721",
    "action": "Marshall D. Teach attacking Jewelry Bonney",
    "attacker_card": "OP09-081",
    "defender_card": "OP07-019"
  },
  "log-290": {
    "player": "TPH64",
    "action": "Jewelry Bonney activated",
    "card": "OP07-019",
    "effect": "Rest Marshall D. Teach",
    "effect_card": "OP09-093"
  },
  "log-291": {
    "player": "TPH64",
    "action": "Discard Jewelry Bonney for Counter 1000",
    "card": "ST02-007"
  },
  "log-292": {
    "player": "Game",
    "action": "Attack Fails",
    "attacker": {
      "card": "OP09-081",
      "power": 5000
    },
    "defender": {
      "card": "OP07-019",
      "power": 6000
    }
  },
  "log-293": {
    "player": "Pirate18721",
    "action": "Shiryu attacking Jewelry Bonney",
    "attacker_card": "OP10-086",
    "defender_card": "OP07-019"
  },
  "log-294": {
    "player": "Game",
    "action": "Jewelry Bonney hit for 1 damage",
    "attacker": {
      "card": "OP10-086",
      "power": 5000
    },
    "defender": {
      "card": "OP07-019",
      "power": 5000
    }
  },
  "log-295": {
    "player": "Pirate18721",
    "action": "Jesus Burgess attacking Jewelry Bonney",
    "attacker_card": "OP09-086",
    "defender_card": "OP07-019"
  },
  "log-296": {
    "player": "TPH64",
    "action": "Killer Blocks",
    "card": "OP01-039"
  },
  "log-297": {
    "player": "Game",
    "action": "Killer Destroyed",
    "attacker": {
      "card": "OP09-086",
      "power": 9000
    },
    "defender": {
      "card": "OP01-039",
      "power": 2000
    }
  },
  "log-298": {
    "player": "Pirate18721",
    "action": "Current Hand",
    "cards": []
  },
  "log-299": {
    "player": "Pirate18721",
    "action": "Current Board",
    "board": [
      "OP10-086",
      "OP09-086",
      "OP09-093"
    ]
  },
  "log-300": {
    "player": "Pirate18721",
    "action": "Current Trash",
    "trash": [
      "OP09-096",
      "OP05-096",
      "OP09-088",
      "OP10-082",
      "OP10-082",
      "OP09-095",
      "OP09-088",
      "OP09-089",
      "OP09-098",
      "OP09-098",
      "OP09-083",
      "OP09-088",
      "OP10-098",
      "EB01-051",
      "EB01-051",
      "OP09-091"
    ]
  },
  "log-301": {
    "player": "Pirate18721",
    "action": "Current Life",
    "life": 3
  },
  "log-302": {
    "player": "TPH64",
    "action": "Current Hand",
    "cards": [
      "OP07-029",
      "OP01-057",
      "EB01-015",
      "OP10-032",
      "OP01-051",
      "EB01-012"
    ]
  },
  "log-303": {
    "player": "TPH64",
    "action": "Current Trash",
    "trash": [
      "EB01-015",
      "ST02-007",
      "OP08-030",
      "OP05-030",
      "ST02-008",
      "OP01-039",
      "OP07-021",
      "OP05-030",
      "ST02-007",
      "ST02-007",
      "EB01-012",
      "OP07-021",
      "OP08-023",
      "ST02-007",
      "OP01-039"
    ]
  },
  "log-304": {
    "player": "TPH64",
    "action": "Current Board",
    "board": [
      "OP01-039"
    ]
  },
  "log-305": {
    "player": "TPH64",
    "action": "Current Life",
    "life": 1
  },
  "log-306": {
    "player": "Pirate18721",
    "action": "End Turn"
  },
  "log-307": {
    "player": "TPH64",
    "action": "Draw 1 Card"
  },
  "log-308": {
    "player": "TPH64",
    "action": "Drew card from deck",
    "card": "OP05-030"
  },
  "log-309": {
    "player": "TPH64",
    "action": "Deploy Donquixote Rosinante",
    "card": "OP05-030"
  },
  "log-310": {
    "player": "TPH64",
    "action": "Deploy Basil Hawkins",
    "card": "OP07-029"
  },
  "log-311": {
    "player": "TPH64",
    "action": "Attach 1 Don to Jewelry Bonney",
    "card": "OP07-019",
    "don_total": 1
  },
  "log-312": {
    "player": "TPH64",
    "action": "Jewelry Bonney attacking Marshall D. Teach",
    "attacker_card": "OP07-019",
    "defender_card": "OP09-081"
  },
  "log-313": {
    "player": "Game",
    "action": "Marshall D. Teach hit for 1 damage",
    "attacker": {
      "card": "OP07-019",
      "power": 6000
    },
    "defender": {
      "card": "OP09-081",
      "power": 5000
    }
  },
  "log-314": {
    "player": "TPH64",
    "action": "End Turn"
  },
  "log-315": {
    "player": "Pirate18721",
    "action": "Current Hand",
    "cards": [
      "OP10-086"
    ]
  },
  "log-316": {
    "player": "Pirate18721",
    "action": "Current Board",
    "board": [
      "OP10-086",
      "OP09-086",
      "OP09-093"
    ]
  },
  "log-317": {
    "player": "Pirate18721",
    "action": "Current Trash",
    "trash": [
      "OP09-096",
      "OP05-096",
      "OP09-088",
      "OP10-082",
      "OP10-082",
      "OP09-095",
      "OP09-088",
      "OP09-089",
      "OP09-098",
      "OP09-098",
      "OP09-083",
      "OP09-088",
      "OP10-098",
      "EB01-051",
      "EB01-051",
      "OP09-091"
    ]
  },
  "log-318": {
    "player": "Pirate18721",
    "action": "Current Life",
    "life": 2
  },
  "log-319": {
    "player": "TPH64",
    "action": "Current Hand",
    "cards": [
      "OP01-057",
      "EB01-015",
      "OP10-032",
      "OP01-051",
      "EB01-012"
    ]
  },
  "log-320": {
    "player": "TPH64",
    "action": "Current Trash",
    "trash": [
      "EB01-015",
      "ST02-007",
      "OP08-030",
      "OP05-030",
      "ST02-008",
      "OP01-039",
      "OP07-021",
      "OP05-030",
      "ST02-007",
      "ST02-007",
      "EB01-012",
      "OP07-021",
      "OP08-023",
      "ST02-007",
      "OP01-039"
    ]
  },
  "log-321": {
    "player": "TPH64",
    "action": "Current Board",
    "board": [
      "OP01-039",
      "OP05-030",
      "OP07-029"
    ]
  },
  "log-322": {
    "player": "TPH64",
    "action": "Current Life",
    "life": 1
  },
  "log-323": {
    "player": "Pirate18721",
    "action": "Draw 1 Card"
  },
  "log-324": {
    "player": "Pirate18721",
    "action": "Drew card from deck",
    "card": "OP10-082"
  },
  "log-325": {
    "player": "Pirate18721",
    "action": "Deploy Shiryu",
    "card": "OP10-086"
  },
  "log-326": {
    "player": "Pirate18721",
    "action": "Shiryu activated",
    "card": "OP10-086",
    "effect": "Destroy Killer",
    "effect_card": "OP01-039"
  },
  "log-327": {
    "player": "Pirate18721",
    "action": "Marshall D. Teach attacking Jewelry Bonney",
    "attacker_card": "OP09-093",
    "defender_card": "OP07-019"
  },
  "log-328": {
    "player": "TPH64",
    "action": "Jewelry Bonney activated",
    "card": "OP07-019",
    "effect": "Rest Jesus Burgess",
    "effect_card": "OP09-086"
  },
  "log-329": {
    "player": "TPH64",
    "action": "Donquixote Rosinante Blocks",
    "card": "OP05-030"
  },
  "log-330": {
    "player": "Game",
    "action": "Donquixote Rosinante Destroyed",
    "attacker": {
      "card": "OP09-093",
      "power": 12000
    },
    "defender": {
      "card": "OP05-030",
      "power": 1000
    }
  },
  "log-331": {
    "player": "Pirate18721",
    "action": "Attach 3 Don to Shiryu",
    "card": "OP10-086",
    "don_total": 3
  },
  "log-332": {
    "player": "Pirate18721",
    "action": "Shiryu attacking Jewelry Bonney",
    "attacker_card": "OP10-086",
    "defender_card": "OP07-019"
  },
  "log-333": {
    "player": "TPH64",
    "action": "Discard Scratchmen Apoo for Counter 2000",
    "card": "EB01-015"
  },
  "log-334": {
    "player": "TPH64",
    "action": "Discard Tashigi for Counter 2000",
    "card": "OP10-032"
  },
  "log-335": {
    "player": "Game",
    "action": "Attack Fails",
    "attacker": {
      "card": "OP10-086",
      "power": 8000
    },
    "defender": {
      "card": "OP07-019",
      "power": 9000
    }
  },
  "log-336": {
    "player": "Pirate18721",
    "action": "Attach 3 Don to Marshall D. Teach",
    "card": "OP09-081",
    "don_total": 3
  },
  "log-337": {
    "player": "Pirate18721",
    "action": "Marshall D. Teach attacking Jewelry Bonney",
    "attacker_card": "OP09-081",
    "defender_card": "OP07-019"
  },
  "log-338": {
    "player": "Game",
    "action": "Jewelry Bonney hit for 1 damage",
    "attacker": {
      "card": "OP09-081",
      "power": 8000
    },
    "defender": {
      "card": "OP07-019",
      "power": 5000
    }
  },
  "log-339": {
    "player": "Pirate18721",
    "action": "Marshall D. Teach activated",
    "card": "OP09-081",
    "effect": "Trash Kuzan",
    "effect_card": "OP10-082"
  },
  "log-340": {
    "player": "Pirate18721",
    "action": "Marshall D. Teach activated",
    "card": "OP09-081",
    "effect": "Opponent can't activate On Play abilities next turn!"
  },
  "log-341": {
    "player": "Pirate18721",
    "action": "Current Hand",
    "cards": []
  },
  "log-342": {
    "player": "Pirate18721",
    "action": "Current Board",
    "board": [
      "OP10-086",
      "OP09-086",
      "OP09-093",
      "OP10-086"
    ]
  },
  "log-343": {
    "player": "Pirate18721",
    "action": "Current Trash",
    "trash": [
      "OP09-096",
      "OP05-096",
      "OP09-088",
      "OP10-082",
      "OP10-082",
      "OP09-095",
      "OP09-088",
      "OP09-089",
      "OP09-098",
      "OP09-098",
      "OP09-083",
      "OP09-088",
      "OP10-098",
      "EB01-051",
      "EB01-051",
      "OP09-091",
      "OP10-082"
    ]
  },
  "log-344": {
    "player": "Pirate18721",
    "action": "Current Life",
    "life": 2
  },
  "log-345": {
    "player": "TPH64",
    "action": "Current Hand",
    "cards": [
      "OP01-057",
      "OP01-051",
      "EB01-012",
      "OP06-035"
    ]
  },
  "log-346": {
    "player": "TPH64",
    "action": "Current Trash",
    "trash": [
      "EB01-015",
      "ST02-007",
      "OP08-030",
      "OP05-030",
      "ST02-008",
      "OP01-039",
      "OP07-021",
      "OP05-030",
      "ST02-007",
      "ST02-007",
      "EB01-012",
      "OP07-021",
      "OP08-023",
      "ST02-007",
      "OP01-039",
      "OP01-039",
      "OP05-030",
      "EB01-015",
      "OP10-032"
    ]
  },
  "log-347": {
    "player": "TPH64",
    "action": "Current Board",
    "board": [
      "OP07-029"
    ]
  },
  "log-348": {
    "player": "TPH64",
    "action": "Current Life",
    "life": 0
  },
  "log-349": {
    "player": "Pirate18721",
    "action": "End Turn"
  },
  "log-350": {
    "player": "TPH64",
    "action": "Draw 1 Card"
  },
  "log-351": {
    "player": "TPH64",
    "action": "Drew card from deck",
    "card": "EB01-015"
  },
  "log-352": {
    "player": "TPH64",
    "action": "Basil Hawkins attacking Marshall D. Teach",
    "attacker_card": "OP07-029",
    "defender_card": "OP09-081"
  },
  "log-353": {
    "player": "Game",
    "action": "Marshall D. Teach hit for 1 damage",
    "attacker": {
      "card": "OP07-029",
      "power": 7000
    },
    "defender": {
      "card": "OP09-081",
      "power": 5000
    }
  },
  "log-354": {
    "player": "TPH64",
    "action": "Attach 3 Don to Jewelry Bonney",
    "card": "OP07-019",
    "don_total": 3
  },
  "log-355": {
    "player": "TPH64",
    "action": "Jewelry Bonney attacking Marshall D. Teach",
    "attacker_card": "OP07-019",
    "defender_card": "OP09-081"
  },
  "log-356": {
    "player": "Game",
    "action": "Marshall D. Teach hit for 1 damage",
    "attacker": {
      "card": "OP07-019",
      "power": 8000
    },
    "defender": {
      "card": "OP09-081",
      "power": 5000
    }
  },
  "log-357": {
    "player": "TPH64",
    "action": "Deploy Hody Jones",
    "card": "OP06-035"
  },
  "log-358": {
    "player": "TPH64",
    "action": "Hody Jones attacking Marshall D. Teach",
    "attacker_card": "OP06-035",
    "defender_card": "OP09-081"
  },
  "log-359": {
    "player": "Pirate18721",
    "action": "Discard Stronger for Counter 2000",
    "card": "OP09-089"
  },
  "log-360": {
    "player": "Pirate18721",
    "action": "Discard Jesus Burgess for Counter 1000",
    "card": "OP09-086"
  },
  "log-361": {
    "player": "Game",
    "action": "Marshall D. Teach hit for 1 damage",
    "attacker": {
      "card": "OP06-035",
      "power": 8000
    },
    "defender": {
      "card": "OP09-081",
      "power": 8000
    }
  },
  "log-362": {
    "player": "Pirate18721",
    "action": "Loses"
  }
}